README.txt
setup.cfg
setup.py
docs/HISTORY.txt
pcommerce/__init__.py
pcommerce.core.egg-info/PKG-INFO
pcommerce.core.egg-info/SOURCES.txt
pcommerce.core.egg-info/dependency_links.txt
pcommerce.core.egg-info/entry_points.txt
pcommerce.core.egg-info/namespace_packages.txt
pcommerce.core.egg-info/not-zip-safe
pcommerce.core.egg-info/requires.txt
pcommerce.core.egg-info/top_level.txt
pcommerce/core/__init__.py
pcommerce/core/adapters.py
pcommerce/core/address.py
pcommerce/core/config.py
pcommerce/core/configure.zcml
pcommerce/core/currency.py
pcommerce/core/events.py
pcommerce/core/interfaces.py
pcommerce/core/order.py
pcommerce/core/permissions.zcml
pcommerce/core/utility.py
pcommerce/core/browser/__init__.py
pcommerce/core/browser/cart.py
pcommerce/core/browser/checkout.py
pcommerce/core/browser/configure.zcml
pcommerce/core/browser/views.py
pcommerce/core/browser/images/price_icon.gif
pcommerce/core/browser/images/product_icon.gif
pcommerce/core/browser/images/variation_icon.gif
pcommerce/core/browser/portlets/__init__.py
pcommerce/core/browser/portlets/cart.py
pcommerce/core/browser/portlets/configure.zcml
pcommerce/core/browser/portlets/templates/cart.pt
pcommerce/core/browser/templates/cart.pt
pcommerce/core/browser/templates/checkout.pt
pcommerce/core/browser/templates/checkout_info.pt
pcommerce/core/browser/templates/checkout_post.pt
pcommerce/core/browser/templates/checkout_pre.pt
pcommerce/core/browser/templates/configlet.pt
pcommerce/core/browser/templates/folder.pt
pcommerce/core/browser/templates/images.pt
pcommerce/core/browser/templates/macros.pt
pcommerce/core/browser/templates/prices.pt
pcommerce/core/browser/templates/product.pt
pcommerce/core/browser/templates/variation.pt
pcommerce/core/browser/templates/variations.pt
pcommerce/core/browser/viewlets/__init__.py
pcommerce/core/browser/viewlets/buy.py
pcommerce/core/browser/viewlets/configure.zcml
pcommerce/core/browser/viewlets/hot.py
pcommerce/core/browser/viewlets/info.py
pcommerce/core/browser/viewlets/new.py
pcommerce/core/browser/viewlets/processor.py
pcommerce/core/browser/viewlets/related.py
pcommerce/core/browser/viewlets/variation.py
pcommerce/core/browser/viewlets/templates/buy.pt
pcommerce/core/browser/viewlets/templates/hot.pt
pcommerce/core/browser/viewlets/templates/info.pt
