Metadata-Version: 1.0
Name: pcommerce.core
Version: 0.4
Summary: eCommerce for Plone
Home-page: http://raptus.com
Author: Raptus AG
Author-email: skaeser@raptus.com
License: GPL
Keywords: plone ecommerce shop
Platform: UNKNOWN
Classifier: Programming Language :: Python
Classifier: Topic :: Software Development :: Libraries :: Python Modules
